dig_ini_editor/__init__.py
dig_ini_editor/__main__.py
dig_ini_editor/arguments.py
dig_ini_editor/editor.py
dig_ini_editor/main.py
dig_ini_editor-1.0.1.dist-info/METADATA
dig_ini_editor-1.0.1.dist-info/WHEEL
dig_ini_editor-1.0.1.dist-info/entry_points.txt
dig_ini_editor-1.0.1.dist-info/top_level.txt
dig_ini_editor-1.0.1.dist-info/RECORD
