Metadata-Version: 2.1
Name: dig-ini-editor
Version: 1.0.1
Summary: Command line INI editor
Home-page: https://github.com/DIG-/python-git-ignore
Author: Gustavo de Oliveira Silva (DIG)
License: CC BY-ND 4.0
Project-URL: Bug Tracker, https://github.com/DIG-/python-git-ignore/issues
Keywords: ini ini-editor inieditor initool
Classifier: Environment :: Console
Classifier: Intended Audience :: Developers
Classifier: Operating System :: OS Independent
Classifier: Topic :: Utilities
Classifier: Programming Language :: Python :: 3
Classifier: Programming Language :: Python :: 3.7
Classifier: Programming Language :: Python :: 3.8
Classifier: Programming Language :: Python :: 3.9
Classifier: Programming Language :: Python :: 3.10
Classifier: Programming Language :: Python :: 3.11
Classifier: Programming Language :: Python :: 3.12
Requires-Python: >=3.7
